piraye/__init__.py
piraye/tasks/__init__.py
piraye/tasks/normalizer/__init__.py
piraye/tasks/normalizer/char_config.py
piraye/tasks/normalizer/mappings.py
piraye/tasks/normalizer/normalization_result.py
piraye/tasks/normalizer/normalizer_builder.py
piraye/tasks/normalizer/data/alphabets/ar.json
piraye/tasks/normalizer/data/alphabets/en.json
piraye/tasks/normalizer/data/alphabets/fa.json
piraye/tasks/normalizer/data/digits/digits.json
piraye/tasks/normalizer/data/others/deletions.json
piraye/tasks/normalizer/data/others/diacritics.json
piraye/tasks/normalizer/data/others/spaces.json
piraye/tasks/normalizer/data/puncs/puncs.json
piraye/tasks/normalizer/normalizers/__init__.py
piraye/tasks/normalizer/normalizers/base_normalizer.py
piraye/tasks/normalizer/normalizers/character_normalizer.py
piraye/tasks/normalizer/normalizers/multi_lingual_normalizer.py
piraye/tasks/normalizer/normalizers/multi_lingual_normalizer_builder.py
piraye/tasks/tokenizer/__init__.py
piraye/tasks/tokenizer/pipeline.py
piraye/tasks/tokenizer/token.py
piraye/tasks/tokenizer/tokenizers/__init__.py
piraye/tasks/tokenizer/tokenizers/base_tokenizer.py
piraye/tasks/tokenizer/tokenizers/nltk_tokenizer.py
piraye/tasks/tokenizer/tokenizers/paragraph_tokenizer.py
piraye/tasks/tokenizer/tokenizers/spacy_tokenizer.py
piraye/tasks/tokenizer/tokenizers/regex_tokenizers/__init__.py
piraye/tasks/tokenizer/tokenizers/regex_tokenizers/base_regex_tokenizer.py
piraye/tasks/tokenizer/tokenizers/regex_tokenizers/email_tokenizer.py
piraye/tasks/tokenizer/tokenizers/regex_tokenizers/html_tokenizer.py
piraye/tasks/tokenizer/tokenizers/regex_tokenizers/url_tokenizer.py
piraye-1.0.0.dist-info/licenses/LICENSE
piraye-1.0.0.dist-info/METADATA
piraye-1.0.0.dist-info/WHEEL
piraye-1.0.0.dist-info/top_level.txt
piraye-1.0.0.dist-info/RECORD
