Metadata-Version: 2.4
Name: piraye
Version: 1.0.0
Summary: A utility for normalizing persian, arabic and english texts
Author-email: Hamed Khademi Khaledi <khaledihkh@gmail.com>, HosseiN Khademi khaeldi <hossein@arusha.dev>, Majid Asgiar Bidhendi <majid@arusha.dev>
Maintainer-email: Arusha Developers <info@arusha.dev>
License: LGPLv2
Project-URL: Homepage, https://github.com/arushadev/piraye
Project-URL: Bug Tracker, https://github.com/arushadev/piraye/issues
Keywords: NLP,Natural Language Processing,Tokenizing,Normalization
Classifier: Development Status :: 2 - Pre-Alpha
Classifier: Intended Audience :: Developers
Classifier: Intended Audience :: Education
Classifier: Intended Audience :: Science/Research
Classifier: License :: OSI Approved :: GNU Lesser General Public License v2 (LGPLv2)
Classifier: Operating System :: OS Independent
Classifier: Programming Language :: Python :: 3.11
Classifier: Programming Language :: Python :: 3.12
Classifier: Topic :: Scientific/Engineering
Classifier: Topic :: Scientific/Engineering :: Artificial Intelligence
Classifier: Topic :: Text Processing
Classifier: Topic :: Text Processing :: Filters
Classifier: Topic :: Text Processing :: General
Classifier: Topic :: Text Processing :: Linguistic
Classifier: Topic :: Utilities
Requires-Python: >=3.11
License-File: LICENSE
Requires-Dist: nltk
Provides-Extra: full
Requires-Dist: lingua-language-detector; extra == "full"
Requires-Dist: spacy; extra == "full"
Dynamic: license-file
